enview/__init__.py
enview/enview.py
enview/commands/__init__.py
enview/commands/enviewcmd.py
enviewcmd/__init__.py
enviewcmd/enviewcmd.py
enview-1.0.4.dist-info/LICENSE
enview-1.0.4.dist-info/METADATA
enview-1.0.4.dist-info/WHEEL
enview-1.0.4.dist-info/entry_points.txt
enview-1.0.4.dist-info/top_level.txt
enview-1.0.4.dist-info/RECORD
