Metadata-Version: 2.1
Name: enview
Version: 1.0.4
Summary: UNKNOWN
Home-page: https://github.com/Chivier/enview
Author: Chivier Humber
Author-email: chivier.humber@outlook.com
License: Apache-2.0 License
Keywords: translator
Platform: UNKNOWN
License-File: LICENSE
Requires-Dist: click (==8.0.3)
Requires-Dist: fuzzywuzzy (==0.18.0)
Requires-Dist: jellyfish (==0.9.0)
Requires-Dist: mypy-extensions (==0.4.3)
Requires-Dist: pathspec (==0.9.0)
Requires-Dist: platformdirs (==2.4.1)
Requires-Dist: prettytable (==3.0.0)
Requires-Dist: prompt-toolkit (==3.0.26)
Requires-Dist: Pygments (==2.11.2)
Requires-Dist: pyparsing (==3.0.7)
Requires-Dist: python-nubia (==0.2b5)
Requires-Dist: readchar (==3.0.5)
Requires-Dist: termcolor (==1.1.0)
Requires-Dist: tomli (==1.2.3)
Requires-Dist: typing-inspect (==0.7.1)
Requires-Dist: typing-extensions (==4.0.1)
Requires-Dist: wcwidth (==0.2.5)
